mongo_odm/__init__.py
mongo_odm/config.py
mongo_odm/cursor.py
mongo_odm/documents.py
mongo_odm/exceptions.py
mongo_odm/fields.py
mongo_odm/managers.py
mongo_odm/registry.py
mongo_odm/utils.py
mongo_odm-1.0.1.dist-info/LICENSE
mongo_odm-1.0.1.dist-info/WHEEL
mongo_odm-1.0.1.dist-info/METADATA
mongo_odm-1.0.1.dist-info/RECORD
