Metadata-Version: 2.1
Name: mongo-odm
Version: 1.0.1
Summary: Python async mongodb ODM using motor and pydantic
License: MIT
Author: Ramzi Tannous
Author-email: ramzi271996@gmail.com
Requires-Python: >=3.7,<4.0
Classifier: License :: OSI Approved :: MIT License
Classifier: Programming Language :: Python :: 3
Classifier: Programming Language :: Python :: 3.7
Classifier: Programming Language :: Python :: 3.8
Classifier: Programming Language :: Python :: 3.9
Requires-Dist: motor (>=2.1.0,<=2.4.0)
Requires-Dist: pydantic (>=1.6.0,<1.9.0)
